{"id": 187265, "media_id": "1027013", "title": {"english": "(C85) [Ourindou (Orikawa)] Secret Sisters (THE IDOLM@STER CINDERELLA GIRLS)", "japanese": "(C85) [\u738b\u6797\u5802 (\u304a\u308a\u304b\u308f)] \u30b7\u30fc\u30af\u30ec\u30c3\u30c8\u30b7\u30b9\u30bf\u30fc\u30ba (\u30a2\u30a4\u30c9\u30eb\u30de\u30b9\u30bf\u30fc \u30b7\u30f3\u30c7\u30ec\u30e9\u30ac\u30fc\u30eb\u30ba)", "chinese": null, "pretty": "Secret Sisters"}, "languages": [{"id": 6346, "type": "language", "name": "japanese", "url": "https://nhentai.net/language/japanese/", "count": 191613}], "cover": {"media_id": "1027013", "width": 350, "height": 498, "mime": "png", "src": "https://t.nhentai.net/galleries/1027013/cover.png"}, "url": "https://nhentai.net/g/187265", "tags": [{"id": 62636, "type": "group", "name": "ourindou", "url": "https://nhentai.net/group/ourindou/", "count": 3}, {"id": 15348, "type": "tag", "name": "ffm threesome", "url": "https://nhentai.net/tag/ffm-threesome/", "count": 17957}, {"id": 8010, "type": "tag", "name": "group", "url": "https://nhentai.net/tag/group/", "count": 72150}, {"id": 25695, "type": "character", "name": "mika jougasaki", "url": "https://nhentai.net/character/mika-jougasaki/", "count": 391}, {"id": 389, "type": "character", "name": "rika jougasaki", "url": "https://nhentai.net/character/rika-jougasaki/", "count": 351}, {"id": 19440, "type": "tag", "name": "lolicon", "url": "https://nhentai.net/tag/lolicon/", "count": 69490}, {"id": 20925, "type": "parody", "name": "the idolmaster", "url": "https://nhentai.net/parody/the-idolmaster/", "count": 8696}, {"id": 33172, "type": "category", "name": "doujinshi", "url": "https://nhentai.net/category/doujinshi/", "count": 228729}, {"id": 6346, "type": "language", "name": "japanese", "url": "https://nhentai.net/language/japanese/", "count": 191613}, {"id": 50627, "type": "artist", "name": "orikawa", "url": "https://nhentai.net/artist/orikawa/", "count": 17}]}