{"id": 189026, "media_id": "1034282", "title": {"english": "(SPARK11) [Affidavit, Kazamichizu (Kyoko, Kazami Aki)] Sameta yoru no kienai netsu (Prince of Stride)", "japanese": "(SPARK11) [Affidavit\u3001\u98a8\u6d77\u5730\u56f3 (\u97ff\u80e1\u3001\u98a8\u6d77\u8061)] \u3055\u3081\u305f\u591c\u306e\u6d88\u3048\u306a\u3044\u71b1 (\u30d7\u30ea\u30f3\u30b9\u30fb\u30aa\u30d6\u30fb\u30b9\u30c8\u30e9\u30a4\u30c9)", "chinese": null, "pretty": "Sameta yoru no kienai netsu"}, "languages": [{"id": 6346, "type": "language", "name": "japanese", "url": "https://nhentai.net/language/japanese/", "count": 191613}], "cover": {"media_id": "1034282", "width": 350, "height": 245, "mime": "jpg", "src": "https://t.nhentai.net/galleries/1034282/cover.jpg"}, "url": "https://nhentai.net/g/189026", "tags": [{"id": 70676, "type": "artist", "name": "kazami aki", "url": "https://nhentai.net/artist/kazami-aki/", "count": 2}, {"id": 70677, "type": "artist", "name": "kyoko", "url": "https://nhentai.net/artist/kyoko/", "count": 2}, {"id": 70678, "type": "group", "name": "affidavit", "url": "https://nhentai.net/group/affidavit/", "count": 2}, {"id": 70679, "type": "group", "name": "kazamichizu", "url": "https://nhentai.net/group/kazamichizu/", "count": 2}, {"id": 26130, "type": "tag", "name": "fingering", "url": "https://nhentai.net/tag/fingering/", "count": 5148}, {"id": 1643, "type": "tag", "name": "kissing", "url": "https://nhentai.net/tag/kissing/", "count": 4312}, {"id": 25871, "type": "tag", "name": "lingerie", "url": "https://nhentai.net/tag/lingerie/", "count": 7659}, {"id": 266, "type": "tag", "name": "sundress", "url": "https://nhentai.net/tag/sundress/", "count": 1065}, {"id": 7752, "type": "tag", "name": "schoolboy uniform", "url": "https://nhentai.net/tag/schoolboy-uniform/", "count": 12311}, {"id": 36789, "type": "parody", "name": "prince of stride", "url": "https://nhentai.net/parody/prince-of-stride/", "count": 3}, {"id": 33172, "type": "category", "name": "doujinshi", "url": "https://nhentai.net/category/doujinshi/", "count": 228729}, {"id": 6346, "type": "language", "name": "japanese", "url": "https://nhentai.net/language/japanese/", "count": 191613}, {"id": 70957, "type": "character", "name": "nana sakurai", "url": "https://nhentai.net/character/nana-sakurai/", "count": 2}, {"id": 70958, "type": "character", "name": "reiji suwa", "url": "https://nhentai.net/character/reiji-suwa/", "count": 2}]}