{"id": 189218, "media_id": "1035028", "title": {"english": "(C91) [Dodo Fuguri (Shindou)] Oni no Oyako wa Hito no Osu to Kozukuri ga Shitai -Haha Hen- [Chinese] [\u7a7a\u9748\u4e4b\u5916\u4e2a\u4eba\u6f22\u5316]", "japanese": "(C91) [\u767e\u3005\u3075\u3050\u308a (\u3057\u3093\u3069\u3046)] \u9b3c\u306e\u6bcd\u5a18\u306f\u30d2\u30c8\u306e\u30aa\u30b9\u3068\u5b50\u3065\u304f\u308a\u304c\u3057\u305f\u3044\uff5e\u6bcd\u7de8\uff5e [\u4e2d\u56fd\u7ffb\u8a33]", "chinese": null, "pretty": "Oni no Oyako wa Hito no Osu to Kozukuri ga Shitai"}, "languages": [{"id": 29963, "type": "language", "name": "chinese", "url": "https://nhentai.net/language/chinese/", "count": 44293}, {"id": 17249, "type": "language", "name": "translated", "url": "https://nhentai.net/language/translated/", "count": 109734}], "cover": {"media_id": "1035028", "width": 349, "height": 246, "mime": "jpg", "src": "https://t.nhentai.net/galleries/1035028/cover.jpg"}, "url": "https://nhentai.net/g/189218", "tags": [{"id": 35763, "type": "tag", "name": "sole male", "url": "https://nhentai.net/tag/sole-male/", "count": 60070}, {"id": 25865, "type": "group", "name": "dodo fuguri", "url": "https://nhentai.net/group/dodo-fuguri/", "count": 92}, {"id": 2937, "type": "tag", "name": "big breasts", "url": "https://nhentai.net/tag/big-breasts/", "count": 103273}, {"id": 29859, "type": "tag", "name": "blowjob", "url": "https://nhentai.net/tag/blowjob/", "count": 37321}, {"id": 15408, "type": "tag", "name": "femdom", "url": "https://nhentai.net/tag/femdom/", "count": 17418}, {"id": 1033, "type": "tag", "name": "handjob", "url": "https://nhentai.net/tag/handjob/", "count": 5884}, {"id": 29631, "type": "tag", "name": "inverted nipples", "url": "https://nhentai.net/tag/inverted-nipples/", "count": 2996}, {"id": 1207, "type": "tag", "name": "milf", "url": "https://nhentai.net/tag/milf/", "count": 22588}, {"id": 13720, "type": "tag", "name": "nakadashi", "url": "https://nhentai.net/tag/nakadashi/", "count": 42357}, {"id": 1037, "type": "tag", "name": "oni", "url": "https://nhentai.net/tag/oni/", "count": 1720}, {"id": 29963, "type": "language", "name": "chinese", "url": "https://nhentai.net/language/chinese/", "count": 44293}, {"id": 17249, "type": "language", "name": "translated", "url": "https://nhentai.net/language/translated/", "count": 109734}, {"id": 27992, "type": "artist", "name": "shindou", "url": "https://nhentai.net/artist/shindou/", "count": 208}, {"id": 33172, "type": "category", "name": "doujinshi", "url": "https://nhentai.net/category/doujinshi/", "count": 228729}, {"id": 19440, "type": "tag", "name": "lolicon", "url": "https://nhentai.net/tag/lolicon/", "count": 69490}]}