{"id": 205129, "media_id": "1103582", "title": {"english": "(C92) [abgrund (Saikawa Yusa)] Mesmerism 2 + Natsu no Mesmerism C92 Kaijou Genteiban [Chinese] [\u7121\u90aa\u6c17\u6f22\u5316\u7d44]", "japanese": "(C92) [abgrund (\u3055\u3044\u304b\u308f\u3086\u3055)] \u30e1\u30b9\u30e1\u30ea\u30ba\u30e02 + \u590f\u306e\u30e1\u30b9\u30e1\u30ea\u30ba\u30e0 C92\u4f1a\u5834\u9650\u5b9a\u7248 [\u4e2d\u56fd\u7ffb\u8a33]", "chinese": null, "pretty": "Mesmerism 2 + Natsu no Mesmerism C92 Kaijou Genteiban"}, "languages": [{"id": 29963, "type": "language", "name": "chinese", "url": "https://nhentai.net/language/chinese/", "count": 44293}, {"id": 17249, "type": "language", "name": "translated", "url": "https://nhentai.net/language/translated/", "count": 109734}], "cover": {"media_id": "1103582", "width": 350, "height": 497, "mime": "jpg", "src": "https://t.nhentai.net/galleries/1103582/cover.jpg"}, "url": "https://nhentai.net/g/205129", "tags": [{"id": 73750, "type": "tag", "name": "bald", "url": "https://nhentai.net/tag/bald/", "count": 2552}, {"id": 19018, "type": "tag", "name": "dark skin", "url": "https://nhentai.net/tag/dark-skin/", "count": 21056}, {"id": 29013, "type": "tag", "name": "dilf", "url": "https://nhentai.net/tag/dilf/", "count": 15244}, {"id": 35763, "type": "tag", "name": "sole male", "url": "https://nhentai.net/tag/sole-male/", "count": 60070}, {"id": 28550, "type": "tag", "name": "teacher", "url": "https://nhentai.net/tag/teacher/", "count": 9616}, {"id": 19362, "type": "group", "name": "abgrund", "url": "https://nhentai.net/group/abgrund/", "count": 226}, {"id": 19175, "type": "tag", "name": "bikini", "url": "https://nhentai.net/tag/bikini/", "count": 11157}, {"id": 20617, "type": "tag", "name": "mind control", "url": "https://nhentai.net/tag/mind-control/", "count": 9174}, {"id": 10314, "type": "tag", "name": "schoolgirl uniform", "url": "https://nhentai.net/tag/schoolgirl-uniform/", "count": 56168}, {"id": 35762, "type": "tag", "name": "sole female", "url": "https://nhentai.net/tag/sole-female/", "count": 66202}, {"id": 3735, "type": "tag", "name": "swimsuit", "url": "https://nhentai.net/tag/swimsuit/", "count": 19363}, {"id": 29963, "type": "language", "name": "chinese", "url": "https://nhentai.net/language/chinese/", "count": 44293}, {"id": 17249, "type": "language", "name": "translated", "url": "https://nhentai.net/language/translated/", "count": 109734}, {"id": 17295, "type": "artist", "name": "saikawa yusa", "url": "https://nhentai.net/artist/saikawa-yusa/", "count": 177}, {"id": 33172, "type": "category", "name": "doujinshi", "url": "https://nhentai.net/category/doujinshi/", "count": 228729}, {"id": 29859, "type": "tag", "name": "blowjob", "url": "https://nhentai.net/tag/blowjob/", "count": 37321}, {"id": 19899, "type": "tag", "name": "exhibitionism", "url": "https://nhentai.net/tag/exhibitionism/", "count": 8575}]}