{"id": 219326, "media_id": "1164492", "title": {"english": "(C93) [Circle Shakunetsu (Sabaku Chitai)] Takebe Saori ga Shojo nanoni PinSalo de Hataraku Hon (Girls und Panzer)", "japanese": "(C93) [\u30b5\u30fc\u30af\u30eb\u707c\u71b1 (\u7802\u6f20)] \u6b66\u90e8\u6c99\u7e54\u304c\u51e6\u5973\u306a\u306e\u306b\u30d4\u30f3\u30b5\u30ed\u3067\u50cd\u304f\u672c (\u30ac\u30fc\u30eb\u30ba&\u30d1\u30f3\u30c4\u30a1\u30fc)", "chinese": null, "pretty": "Takebe Saori ga Shojo nanoni PinSalo de Hataraku Hon"}, "languages": [{"id": 6346, "type": "language", "name": "japanese", "url": "https://nhentai.net/language/japanese/", "count": 191613}], "cover": {"media_id": "1164492", "width": 350, "height": 508, "mime": "jpg", "src": "https://t.nhentai.net/galleries/1164492/cover.jpg"}, "url": "https://nhentai.net/g/219326", "tags": [{"id": 52510, "type": "group", "name": "circle shakunetsu", "url": "https://nhentai.net/group/circle-shakunetsu/", "count": 8}, {"id": 52511, "type": "artist", "name": "sabaku chitai", "url": "https://nhentai.net/artist/sabaku-chitai/", "count": 14}, {"id": 11387, "type": "character", "name": "saori takebe", "url": "https://nhentai.net/character/saori-takebe/", "count": 109}, {"id": 35762, "type": "tag", "name": "sole female", "url": "https://nhentai.net/tag/sole-female/", "count": 66202}, {"id": 391, "type": "parody", "name": "girls und panzer", "url": "https://nhentai.net/parody/girls-und-panzer/", "count": 1846}, {"id": 33172, "type": "category", "name": "doujinshi", "url": "https://nhentai.net/category/doujinshi/", "count": 228729}, {"id": 6346, "type": "language", "name": "japanese", "url": "https://nhentai.net/language/japanese/", "count": 191613}, {"id": 12695, "type": "tag", "name": "prostitution", "url": "https://nhentai.net/tag/prostitution/", "count": 5613}, {"id": 29859, "type": "tag", "name": "blowjob", "url": "https://nhentai.net/tag/blowjob/", "count": 37321}, {"id": 29013, "type": "tag", "name": "dilf", "url": "https://nhentai.net/tag/dilf/", "count": 15244}]}