{"id": 235842, "media_id": "1235748", "title": {"english": "(COMIC1\u260611) [Assemblink (Suzuka Sakito)] Langue de Dieu (Shokugeki no Soma)", "japanese": "(COMIC1\u260611) [\u30a2\u30bb\u30f3\u30d6\u30ea\u30f3\u30af (\u6dbc\u52a0\u65e9\u5e0c\u514e)] Langue de Dieu (\u98df\u621f\u306e\u30bd\u30fc\u30de)", "chinese": null, "pretty": "Langue de Dieu"}, "languages": [{"id": 6346, "type": "language", "name": "japanese", "url": "https://nhentai.net/language/japanese/", "count": 191613}], "cover": {"media_id": "1235748", "width": 350, "height": 477, "mime": "jpg", "src": "https://t.nhentai.net/galleries/1235748/cover.jpg"}, "url": "https://nhentai.net/g/235842", "tags": [{"id": 12742, "type": "parody", "name": "shokugeki no soma", "url": "https://nhentai.net/parody/shokugeki-no-soma/", "count": 234}, {"id": 10214, "type": "character", "name": "erina nakiri", "url": "https://nhentai.net/character/erina-nakiri/", "count": 135}, {"id": 49665, "type": "character", "name": "hisako arato", "url": "https://nhentai.net/character/hisako-arato/", "count": 13}, {"id": 10231, "type": "character", "name": "souma yukihira", "url": "https://nhentai.net/character/souma-yukihira/", "count": 92}, {"id": 3493, "type": "group", "name": "assemblink", "url": "https://nhentai.net/group/assemblink/", "count": 20}, {"id": 3416, "type": "artist", "name": "suzuka sakito", "url": "https://nhentai.net/artist/suzuka-sakito/", "count": 20}, {"id": 29859, "type": "tag", "name": "blowjob", "url": "https://nhentai.net/tag/blowjob/", "count": 37321}, {"id": 26130, "type": "tag", "name": "fingering", "url": "https://nhentai.net/tag/fingering/", "count": 5148}, {"id": 25614, "type": "tag", "name": "paizuri", "url": "https://nhentai.net/tag/paizuri/", "count": 22785}, {"id": 14971, "type": "tag", "name": "sex toys", "url": "https://nhentai.net/tag/sex-toys/", "count": 20823}, {"id": 24201, "type": "tag", "name": "stockings", "url": "https://nhentai.net/tag/stockings/", "count": 64784}, {"id": 20035, "type": "tag", "name": "x-ray", "url": "https://nhentai.net/tag/x-ray/", "count": 20947}, {"id": 20905, "type": "tag", "name": "full color", "url": "https://nhentai.net/tag/full-color/", "count": 33404}, {"id": 33172, "type": "category", "name": "doujinshi", "url": "https://nhentai.net/category/doujinshi/", "count": 228729}, {"id": 6346, "type": "language", "name": "japanese", "url": "https://nhentai.net/language/japanese/", "count": 191613}, {"id": 27473, "type": "tag", "name": "mosaic censorship", "url": "https://nhentai.net/tag/mosaic-censorship/", "count": 23707}, {"id": 14283, "type": "tag", "name": "anal", "url": "https://nhentai.net/tag/anal/", "count": 64587}, {"id": 9162, "type": "tag", "name": "masturbation", "url": "https://nhentai.net/tag/masturbation/", "count": 9228}]}