{"id": 248071, "media_id": "1292408", "title": {"english": "(C94) [Project Harakiri (Kaishaku)] BOKUTACHIHA SENSEIMO KAWAII (Bokutachi wa Benkyou ga Dekinai)", "japanese": "(C94) [PROJECT\u30cf\u30e9\u30ad\u30ea (\u4ecb\u932f)] BOKUTACHIHA SENSEIMO KAWAII (\u307c\u304f\u305f\u3061\u306f\u52c9\u5f37\u304c\u3067\u304d\u306a\u3044)", "chinese": null, "pretty": "BOKUTACHIHA SENSEIMO KAWAII"}, "languages": [{"id": 6346, "type": "language", "name": "japanese", "url": "https://nhentai.net/language/japanese/", "count": 191613}], "cover": {"media_id": "1292408", "width": 350, "height": 498, "mime": "jpg", "src": "https://t.nhentai.net/galleries/1292408/cover.jpg"}, "url": "https://nhentai.net/g/248071", "tags": [{"id": 76298, "type": "parody", "name": "bokutachi wa benkyou ga dekinai", "url": "https://nhentai.net/parody/bokutachi-wa-benkyou-ga-dekinai/", "count": 91}, {"id": 6435, "type": "group", "name": "project harakiri", "url": "https://nhentai.net/group/project-harakiri/", "count": 104}, {"id": 28271, "type": "artist", "name": "kaishaku", "url": "https://nhentai.net/artist/kaishaku/", "count": 123}, {"id": 8378, "type": "tag", "name": "glasses", "url": "https://nhentai.net/tag/glasses/", "count": 48279}, {"id": 7752, "type": "tag", "name": "schoolboy uniform", "url": "https://nhentai.net/tag/schoolboy-uniform/", "count": 12311}, {"id": 24380, "type": "tag", "name": "pantyhose", "url": "https://nhentai.net/tag/pantyhose/", "count": 14713}, {"id": 28550, "type": "tag", "name": "teacher", "url": "https://nhentai.net/tag/teacher/", "count": 9616}, {"id": 33172, "type": "category", "name": "doujinshi", "url": "https://nhentai.net/category/doujinshi/", "count": 228729}, {"id": 6346, "type": "language", "name": "japanese", "url": "https://nhentai.net/language/japanese/", "count": 191613}, {"id": 8368, "type": "tag", "name": "full censorship", "url": "https://nhentai.net/tag/full-censorship/", "count": 17000}, {"id": 370, "type": "tag", "name": "business suit", "url": "https://nhentai.net/tag/business-suit/", "count": 3176}]}