{"id": 249825, "media_id": "1300588", "title": {"english": "[Souchou Bazooka (Tsubakiyama Parry)] Aigis H Illustrations (Sennen Sensou Aigis) [Digital]", "japanese": "[\u65e9\u671d\u30d0\u30ba\u30fc\u30ab (\u693f\u5c71\u30d1\u30ea\u30a3)] Aigis H Illustrations (\u5343\u5e74\u6226\u4e89\u30a2\u30a4\u30ae\u30b9) [DL\u7248]", "chinese": null, "pretty": "Aigis H Illustrations"}, "languages": [{"id": 6346, "type": "language", "name": "japanese", "url": "https://nhentai.net/language/japanese/", "count": 191613}], "cover": {"media_id": "1300588", "width": 350, "height": 494, "mime": "jpg", "src": "https://t.nhentai.net/galleries/1300588/cover.jpg"}, "url": "https://nhentai.net/g/249825", "tags": [{"id": 1150, "type": "parody", "name": "sennen sensou aigis", "url": "https://nhentai.net/parody/sennen-sensou-aigis/", "count": 261}, {"id": 67, "type": "group", "name": "souchou bazooka", "url": "https://nhentai.net/group/souchou-bazooka/", "count": 21}, {"id": 29581, "type": "artist", "name": "tsubakiyama parry", "url": "https://nhentai.net/artist/tsubakiyama-parry/", "count": 22}, {"id": 32341, "type": "tag", "name": "shotacon", "url": "https://nhentai.net/tag/shotacon/", "count": 39737}, {"id": 20905, "type": "tag", "name": "full color", "url": "https://nhentai.net/tag/full-color/", "count": 33404}, {"id": 27473, "type": "tag", "name": "mosaic censorship", "url": "https://nhentai.net/tag/mosaic-censorship/", "count": 24088}, {"id": 33172, "type": "category", "name": "doujinshi", "url": "https://nhentai.net/category/doujinshi/", "count": 228729}, {"id": 6346, "type": "language", "name": "japanese", "url": "https://nhentai.net/language/japanese/", "count": 191613}, {"id": 27598, "type": "tag", "name": "low shotacon", "url": "https://nhentai.net/tag/low-shotacon/", "count": 300}, {"id": 19440, "type": "tag", "name": "lolicon", "url": "https://nhentai.net/tag/lolicon/", "count": 69490}, {"id": 14362, "type": "tag", "name": "low lolicon", "url": "https://nhentai.net/tag/low-lolicon/", "count": 1041}]}