{"id": 270794, "media_id": "1407719", "title": {"english": "[Kaoruya (Katutoshi)] Shinobi no Kokoroe (Naruto)", "japanese": "[\u85ab\u5bb6 (\u304b\u3064\u3068\u3057)] \u5fcd\u306e\u5fc3\u5f97 (NARUTO -\u30ca\u30eb\u30c8-)", "chinese": null, "pretty": "Shinobi no Kokoroe"}, "languages": [{"id": 6346, "type": "language", "name": "japanese", "url": "https://nhentai.net/language/japanese/", "count": 191613}], "cover": {"media_id": "1407719", "width": 350, "height": 495, "mime": "jpg", "src": "https://t.nhentai.net/galleries/1407719/cover.jpg"}, "url": "https://nhentai.net/g/270794", "tags": [{"id": 13159, "type": "parody", "name": "naruto", "url": "https://nhentai.net/parody/naruto/", "count": 1267}, {"id": 7718, "type": "character", "name": "naruto uzumaki", "url": "https://nhentai.net/character/naruto-uzumaki/", "count": 634}, {"id": 23963, "type": "character", "name": "orochimaru", "url": "https://nhentai.net/character/orochimaru/", "count": 7}, {"id": 6430, "type": "character", "name": "shikamaru nara", "url": "https://nhentai.net/character/shikamaru-nara/", "count": 33}, {"id": 21712, "type": "tag", "name": "males only", "url": "https://nhentai.net/tag/males-only/", "count": 22165}, {"id": 23895, "type": "tag", "name": "yaoi", "url": "https://nhentai.net/tag/yaoi/", "count": 28480}, {"id": 33172, "type": "category", "name": "doujinshi", "url": "https://nhentai.net/category/doujinshi/", "count": 228729}, {"id": 6346, "type": "language", "name": "japanese", "url": "https://nhentai.net/language/japanese/", "count": 191613}, {"id": 32341, "type": "tag", "name": "shotacon", "url": "https://nhentai.net/tag/shotacon/", "count": 39737}, {"id": 105783, "type": "artist", "name": "katutoshi", "url": "https://nhentai.net/artist/katutoshi/", "count": 3}, {"id": 106429, "type": "group", "name": "kaoruya", "url": "https://nhentai.net/group/kaoruya/", "count": 1}]}