{"id": 271109, "media_id": "1409110", "title": {"english": "(C86) [Mattari House (Aitsu)] Shinyuu no Yome (Majin Bone)", "japanese": "(C86) [\u307e\u3063\u305f\u308a\u30cf\u30a6\u30b9 (\u30a2\u30a4\u30c4)] \u89aa\u53cb\u306e\u5ac1 (\u30de\u30b8\u30f3\u30dc\u30fc\u30f3)", "chinese": null, "pretty": "Shinyuu no Yome"}, "languages": [{"id": 6346, "type": "language", "name": "japanese", "url": "https://nhentai.net/language/japanese/", "count": 191613}], "cover": {"media_id": "1409110", "width": 350, "height": 508, "mime": "jpg", "src": "https://t.nhentai.net/galleries/1409110/cover.jpg"}, "url": "https://nhentai.net/g/271109", "tags": [{"id": 16288, "type": "parody", "name": "majin bone", "url": "https://nhentai.net/parody/majin-bone/", "count": 7}, {"id": 9218, "type": "group", "name": "mattari house", "url": "https://nhentai.net/group/mattari-house/", "count": 24}, {"id": 4194, "type": "artist", "name": "dokokano aitsu", "url": "https://nhentai.net/artist/dokokano-aitsu/", "count": 24}, {"id": 35763, "type": "tag", "name": "sole male", "url": "https://nhentai.net/tag/sole-male/", "count": 60070}, {"id": 2937, "type": "tag", "name": "big breasts", "url": "https://nhentai.net/tag/big-breasts/", "count": 103273}, {"id": 35762, "type": "tag", "name": "sole female", "url": "https://nhentai.net/tag/sole-female/", "count": 66202}, {"id": 33172, "type": "category", "name": "doujinshi", "url": "https://nhentai.net/category/doujinshi/", "count": 228729}, {"id": 6346, "type": "language", "name": "japanese", "url": "https://nhentai.net/language/japanese/", "count": 191613}]}