{"id": 275401, "media_id": "1431128", "title": {"english": "(Puniket 39) [WICKED HEART (ZooTAN)] Pan-chan Renshuuchou (Dragon Ball GT)", "japanese": "(\u3077\u306b\u30b1\u30c3\u30c839) [WICKEDHEART (ZooTAN)] \u30d1\u30f3\u3061\u3083\u3093\u7df4\u7fd2\u5e33 (\u30c9\u30e9\u30b4\u30f3\u30dc\u30fc\u30ebGT)", "chinese": null, "pretty": "Pan-chan Renshuuchou"}, "languages": [{"id": 6346, "type": "language", "name": "japanese", "url": "https://nhentai.net/language/japanese/", "count": 191613}], "cover": {"media_id": "1431128", "width": 350, "height": 490, "mime": "jpg", "src": "https://t.nhentai.net/galleries/1431128/cover.jpg"}, "url": "https://nhentai.net/g/275401", "tags": [{"id": 31947, "type": "parody", "name": "dragon ball gt", "url": "https://nhentai.net/parody/dragon-ball-gt/", "count": 35}, {"id": 12786, "type": "character", "name": "pan", "url": "https://nhentai.net/character/pan/", "count": 47}, {"id": 15194, "type": "group", "name": "wicked heart", "url": "https://nhentai.net/group/wicked-heart/", "count": 74}, {"id": 14479, "type": "artist", "name": "zootan", "url": "https://nhentai.net/artist/zootan/", "count": 86}, {"id": 19440, "type": "tag", "name": "lolicon", "url": "https://nhentai.net/tag/lolicon/", "count": 69490}, {"id": 33172, "type": "category", "name": "doujinshi", "url": "https://nhentai.net/category/doujinshi/", "count": 228729}, {"id": 6346, "type": "language", "name": "japanese", "url": "https://nhentai.net/language/japanese/", "count": 191613}]}