{"id": 299727, "media_id": "1561777", "title": {"english": "Hen na Nee-san Ep9", "japanese": "", "chinese": null, "pretty": "Hen na Nee-san Ep9"}, "languages": [{"id": 12227, "type": "language", "name": "english", "url": "https://nhentai.net/language/english/", "count": 92747}, {"id": 17249, "type": "language", "name": "translated", "url": "https://nhentai.net/language/translated/", "count": 156871}], "cover": {"media_id": "1561777", "width": 350, "height": 518, "mime": "png", "src": "https://t.nhentai.net/galleries/1561777/cover.png"}, "url": "https://nhentai.net/g/299727", "tags": [{"id": 7155, "type": "tag", "name": "cunnilingus", "url": "https://nhentai.net/tag/cunnilingus/", "count": 6800}, {"id": 8050, "type": "tag", "name": "females only", "url": "https://nhentai.net/tag/females-only/", "count": 11469}, {"id": 8378, "type": "tag", "name": "glasses", "url": "https://nhentai.net/tag/glasses/", "count": 58026}, {"id": 12227, "type": "language", "name": "english", "url": "https://nhentai.net/language/english/", "count": 92747}, {"id": 17249, "type": "language", "name": "translated", "url": "https://nhentai.net/language/translated/", "count": 156871}, {"id": 17591, "type": "tag", "name": "robot", "url": "https://nhentai.net/tag/robot/", "count": 1509}, {"id": 19900, "type": "artist", "name": "yoshitomi akihito", "url": "https://nhentai.net/artist/yoshitomi-akihito/", "count": 21}, {"id": 19954, "type": "tag", "name": "yuri", "url": "https://nhentai.net/tag/yuri/", "count": 24404}, {"id": 33172, "type": "category", "name": "doujinshi", "url": "https://nhentai.net/category/doujinshi/", "count": 294682}, {"id": 85295, "type": "tag", "name": "twintails", "url": "https://nhentai.net/tag/twintails/", "count": 16717}]}