{"id": 308701, "media_id": "1611148", "title": {"english": "[Gustav] Sex Takuhaibin [Kanzenban]", "japanese": "[\u3050\u3059\u305f\u3075] \u30bb\u30c3\u30af\u30b9\u5b85\u914d\u4fbf\u3010\u5b8c\u5168\u7248\u3011", "chinese": null, "pretty": "Sex Takuhaibin"}, "languages": [{"id": 6346, "type": "language", "name": "japanese", "url": "https://nhentai.net/language/japanese/", "count": 195352}], "cover": {"media_id": "1611148", "width": 350, "height": 494, "mime": "jpg", "src": "https://t.nhentai.net/galleries/1611148/cover.jpg"}, "url": "https://nhentai.net/g/308701", "tags": [{"id": 11358, "type": "artist", "name": "gustav", "url": "https://nhentai.net/artist/gustav/", "count": 137}, {"id": 24726, "type": "tag", "name": "apron", "url": "https://nhentai.net/tag/apron/", "count": 3001}, {"id": 24201, "type": "tag", "name": "stockings", "url": "https://nhentai.net/tag/stockings/", "count": 66825}, {"id": 8368, "type": "tag", "name": "full censorship", "url": "https://nhentai.net/tag/full-censorship/", "count": 17801}, {"id": 33173, "type": "category", "name": "manga", "url": "https://nhentai.net/category/manga/", "count": 79602}, {"id": 6346, "type": "language", "name": "japanese", "url": "https://nhentai.net/language/japanese/", "count": 195352}, {"id": 9260, "type": "tag", "name": "cheating", "url": "https://nhentai.net/tag/cheating/", "count": 12317}, {"id": 2937, "type": "tag", "name": "big breasts", "url": "https://nhentai.net/tag/big-breasts/", "count": 107028}, {"id": 20362, "type": "tag", "name": "gyaru-oh", "url": "https://nhentai.net/tag/gyaru-oh/", "count": 610}]}