{"id": 332378, "media_id": "1754322", "title": {"english": "[MC] Ore no Chinko o Irete mo Muteikou, Muhannou na Downer-kei Kyonyuu Imouto ni Yaritai Houdai Life", "japanese": "[MC] \u4ffa\u306e\u30c1\u3007\u30b3\u3092\u633f\u308c\u3066\u3082\u7121\u62b5\u6297\u30fb\u7121\u53cd\u5fdc\u306a\u30c0\u30a6\u30ca\u30fc\u7cfb\u5de8\u4e73\u59b9\u306b\u30e4\u308a\u305f\u3044\u653e\u984c\u30e9\u30a4\u30d5", "chinese": null, "pretty": "Ore no Chinko o Irete mo Muteikou, Muhannou na Downer-kei Kyonyuu Imouto ni Yaritai Houdai Life"}, "languages": [{"id": 6346, "type": "language", "name": "japanese", "url": "https://nhentai.net/language/japanese/", "count": 204011}], "cover": {"media_id": "1754322", "width": 350, "height": 525, "mime": "jpg", "src": "https://t.nhentai.net/galleries/1754322/cover.jpg"}, "url": "https://nhentai.net/g/332378", "tags": [{"id": 20510, "type": "group", "name": "mc", "url": "https://nhentai.net/group/mc/", "count": 169}, {"id": 2937, "type": "tag", "name": "big breasts", "url": "https://nhentai.net/tag/big-breasts/", "count": 114855}, {"id": 8516, "type": "tag", "name": "emotionless sex", "url": "https://nhentai.net/tag/emotionless-sex/", "count": 1002}, {"id": 20282, "type": "tag", "name": "footjob", "url": "https://nhentai.net/tag/footjob/", "count": 10036}, {"id": 13720, "type": "tag", "name": "nakadashi", "url": "https://nhentai.net/tag/nakadashi/", "count": 49014}, {"id": 25614, "type": "tag", "name": "paizuri", "url": "https://nhentai.net/tag/paizuri/", "count": 25089}, {"id": 28031, "type": "tag", "name": "sister", "url": "https://nhentai.net/tag/sister/", "count": 15766}, {"id": 22942, "type": "tag", "name": "incest", "url": "https://nhentai.net/tag/incest/", "count": 30832}, {"id": 33173, "type": "category", "name": "manga", "url": "https://nhentai.net/category/manga/", "count": 86288}, {"id": 6346, "type": "language", "name": "japanese", "url": "https://nhentai.net/language/japanese/", "count": 204011}, {"id": 27473, "type": "tag", "name": "mosaic censorship", "url": "https://nhentai.net/tag/mosaic-censorship/", "count": 27454}, {"id": 35763, "type": "tag", "name": "sole male", "url": "https://nhentai.net/tag/sole-male/", "count": 70456}, {"id": 20905, "type": "tag", "name": "full color", "url": "https://nhentai.net/tag/full-color/", "count": 38800}, {"id": 35762, "type": "tag", "name": "sole female", "url": "https://nhentai.net/tag/sole-female/", "count": 77884}, {"id": 90671, "type": "parody", "name": "original", "url": "https://nhentai.net/parody/original/", "count": 28114}]}