{"id": 359402, "media_id": "1912385", "title": {"english": "[Seto Raio] 2-shuukan Prefab Seikatsu (COMIC Masyo 2020-12) [Chinese] [Digital]", "japanese": "[\u702c\u6238\u3089\u3044\u304a] 2\u9031\u9593\u30d7\u30ec\u30cf\u30d6\u751f\u6d3b (\u30b3\u30df\u30c3\u30af\u30fb\u30de\u30b7\u30e7\u30a6 2020\u5e7412\u6708\u53f7) [\u4e2d\u56fd\u7ffb\u8a33] [DL\u7248]", "chinese": null, "pretty": "2-shuukan Prefab Seikatsu"}, "languages": [{"id": 17249, "type": "language", "name": "translated", "url": "https://nhentai.net/language/translated/", "count": 142031}, {"id": 29963, "type": "language", "name": "chinese", "url": "https://nhentai.net/language/chinese/", "count": 63109}], "cover": {"media_id": "1912385", "width": 350, "height": 496, "mime": "jpg", "src": "https://t.nhentai.net/galleries/1912385/cover.jpg"}, "url": "https://nhentai.net/g/359402", "tags": [{"id": 17249, "type": "language", "name": "translated", "url": "https://nhentai.net/language/translated/", "count": 142031}, {"id": 27473, "type": "tag", "name": "mosaic censorship", "url": "https://nhentai.net/tag/mosaic-censorship/", "count": 30724}, {"id": 29366, "type": "tag", "name": "tomboy", "url": "https://nhentai.net/tag/tomboy/", "count": 3359}, {"id": 29963, "type": "language", "name": "chinese", "url": "https://nhentai.net/language/chinese/", "count": 63109}, {"id": 33173, "type": "category", "name": "manga", "url": "https://nhentai.net/category/manga/", "count": 93957}, {"id": 35762, "type": "tag", "name": "sole female", "url": "https://nhentai.net/tag/sole-female/", "count": 88118}, {"id": 35763, "type": "tag", "name": "sole male", "url": "https://nhentai.net/tag/sole-male/", "count": 79596}, {"id": 128651, "type": "artist", "name": "seto raio", "url": "https://nhentai.net/artist/seto-raio/", "count": 4}]}