{"id": 359979, "media_id": "1915806", "title": {"english": "(Drei Schicksale Ende -3-tsu no Unmei no Ketsumatsu-) [SurferFarm (Kanbe Rino)] Kyouetsu no Ayamachi (Fire Emblem: Three Houses)", "japanese": "(Drei Schicksale Ende -3\u3064\u306e\u904b\u547d\u306e\u7d50\u672b-) [SurferFarm (\u30ab\u30f3\u30d9\u308a\u306e)] \u6050\u60a6\u306e\u904e\u3061 (\u30d5\u30a1\u30a4\u30a2\u30fc\u30a8\u30e0\u30d6\u30ec\u30e0 \u98a8\u82b1\u96ea\u6708)", "chinese": null, "pretty": "Kyouetsu no Ayamachi"}, "languages": [{"id": 6346, "type": "language", "name": "japanese", "url": "https://nhentai.net/language/japanese/", "count": 214681}], "cover": {"media_id": "1915806", "width": 350, "height": 502, "mime": "jpg", "src": "https://t.nhentai.net/galleries/1915806/cover.jpg"}, "url": "https://nhentai.net/g/359979", "tags": [{"id": 6346, "type": "language", "name": "japanese", "url": "https://nhentai.net/language/japanese/", "count": 214681}, {"id": 33172, "type": "category", "name": "doujinshi", "url": "https://nhentai.net/category/doujinshi/", "count": 269894}, {"id": 110220, "type": "parody", "name": "fire emblem three houses", "url": "https://nhentai.net/parody/fire-emblem-three-houses/", "count": 65}, {"id": 124377, "type": "character", "name": "edelgard von hresvelg", "url": "https://nhentai.net/character/edelgard-von-hresvelg/", "count": 9}, {"id": 130010, "type": "group", "name": "surferfarm", "url": "https://nhentai.net/group/surferfarm/", "count": 1}, {"id": 130260, "type": "artist", "name": "kanbe rino", "url": "https://nhentai.net/artist/kanbe-rino/", "count": 1}, {"id": 130313, "type": "character", "name": "hubert von vestra", "url": "https://nhentai.net/character/hubert-von-vestra/", "count": 1}]}