{"id": 364737, "media_id": "1948938", "title": {"english": "[Cuvie] Second Virgin (GLOSSY) [Cantonese Translation] [Chinese]", "japanese": "[Cuvie] \u30bb\u30ab\u30f3\u30c9\u30f4\u30a1\u30fc\u30b8\u30f3 (GLOSSY) [\u4e2d\u56fd\u7ffb\u8a33]", "chinese": null, "pretty": "Second Virgin"}, "languages": [{"id": 29963, "type": "language", "name": "chinese", "url": "https://nhentai.net/language/chinese/", "count": 64781}, {"id": 17249, "type": "language", "name": "translated", "url": "https://nhentai.net/language/translated/", "count": 145046}], "cover": {"media_id": "1948938", "width": 350, "height": 496, "mime": "jpg", "src": "https://t.nhentai.net/galleries/1948938/cover.jpg"}, "url": "https://nhentai.net/g/364737", "tags": [{"id": 29963, "type": "language", "name": "chinese", "url": "https://nhentai.net/language/chinese/", "count": 64781}, {"id": 17249, "type": "language", "name": "translated", "url": "https://nhentai.net/language/translated/", "count": 145046}, {"id": 3820, "type": "artist", "name": "cuvie", "url": "https://nhentai.net/artist/cuvie/", "count": 495}, {"id": 35763, "type": "tag", "name": "sole male", "url": "https://nhentai.net/tag/sole-male/", "count": 81311}, {"id": 25601, "type": "tag", "name": "small breasts", "url": "https://nhentai.net/tag/small-breasts/", "count": 8341}, {"id": 35762, "type": "tag", "name": "sole female", "url": "https://nhentai.net/tag/sole-female/", "count": 90163}, {"id": 33173, "type": "category", "name": "manga", "url": "https://nhentai.net/category/manga/", "count": 95428}]}