{"id": 376605, "media_id": "2027476", "title": {"english": "\u91cd\u53e3\u614e\u5165\uff01(C78) [\u30cd\u30b3\u30cd\u30b3\u30fb\u30d1\u30f3\u30c1\u30e5\u30c3! (\u306d\u3053\u306d\u3053\u3071\u3093\u3061\u3085\u3063)] \u4e09\u59c9\u59b9\u8abf\u6559\u904a\u622f\u3010\u7531\u9999\u91cc\u7de8\u3011\u3086\u304b\u308a\u3061\u3083\u3093\u306e\u8c5a\u9f3b\u5bb6\u755c\u8abf\u6559\u3010\u30a2\u30ca\u30eb\u88ab\u8650\u6388\u696d\u3011", "japanese": "", "chinese": null, "pretty": "\u91cd\u53e3\u614e\u5165\uff01\u4e09\u59c9\u59b9\u8abf\u6559\u904a\u622f\u3010\u7531\u9999\u91cc\u7de8\u3011\u3086\u304b\u308a\u3061\u3083\u3093\u306e\u8c5a\u9f3b\u5bb6\u755c\u8abf\u6559\u3010\u30a2\u30ca\u30eb\u88ab\u8650\u6388\u696d\u3011"}, "languages": [{"id": 17249, "type": "language", "name": "translated", "url": "https://nhentai.net/language/translated/", "count": 151388}, {"id": 29963, "type": "language", "name": "chinese", "url": "https://nhentai.net/language/chinese/", "count": 68734}], "cover": {"media_id": "2027476", "width": 350, "height": 497, "mime": "jpg", "src": "https://t.nhentai.net/galleries/2027476/cover.jpg"}, "url": "https://nhentai.net/g/376605", "tags": [{"id": 2820, "type": "tag", "name": "scat", "url": "https://nhentai.net/tag/scat/", "count": 6985}, {"id": 4549, "type": "tag", "name": "torture", "url": "https://nhentai.net/tag/torture/", "count": 2376}, {"id": 5529, "type": "tag", "name": "urethra insertion", "url": "https://nhentai.net/tag/urethra-insertion/", "count": 3605}, {"id": 5820, "type": "tag", "name": "piercing", "url": "https://nhentai.net/tag/piercing/", "count": 7382}, {"id": 8378, "type": "tag", "name": "glasses", "url": "https://nhentai.net/tag/glasses/", "count": 57474}, {"id": 9406, "type": "tag", "name": "enema", "url": "https://nhentai.net/tag/enema/", "count": 3901}, {"id": 14283, "type": "tag", "name": "anal", "url": "https://nhentai.net/tag/anal/", "count": 79431}, {"id": 17249, "type": "language", "name": "translated", "url": "https://nhentai.net/language/translated/", "count": 151388}, {"id": 18328, "type": "tag", "name": "thigh high boots", "url": "https://nhentai.net/tag/thigh-high-boots/", "count": 4560}, {"id": 19426, "type": "tag", "name": "pig girl", "url": "https://nhentai.net/tag/pig-girl/", "count": 110}, {"id": 28119, "type": "tag", "name": "nose hook", "url": "https://nhentai.net/tag/nose-hook/", "count": 1111}, {"id": 28778, "type": "tag", "name": "large insertions", "url": "https://nhentai.net/tag/large-insertions/", "count": 1743}, {"id": 29963, "type": "language", "name": "chinese", "url": "https://nhentai.net/language/chinese/", "count": 68734}, {"id": 31687, "type": "tag", "name": "randoseru", "url": "https://nhentai.net/tag/randoseru/", "count": 1191}, {"id": 31846, "type": "tag", "name": "body writing", "url": "https://nhentai.net/tag/body-writing/", "count": 1323}, {"id": 33172, "type": "category", "name": "doujinshi", "url": "https://nhentai.net/category/doujinshi/", "count": 282532}, {"id": 35762, "type": "tag", "name": "sole female", "url": "https://nhentai.net/tag/sole-female/", "count": 95050}, {"id": 75144, "type": "artist", "name": "nekoneko panchu", "url": "https://nhentai.net/artist/nekoneko-panchu/", "count": 6}, {"id": 81774, "type": "tag", "name": "kemonomimi", "url": "https://nhentai.net/tag/kemonomimi/", "count": 10599}, {"id": 85295, "type": "tag", "name": "twintails", "url": "https://nhentai.net/tag/twintails/", "count": 15522}, {"id": 90671, "type": "parody", "name": "original", "url": "https://nhentai.net/parody/original/", "count": 42026}, {"id": 104227, "type": "tag", "name": "tail", "url": "https://nhentai.net/tag/tail/", "count": 3945}, {"id": 105833, "type": "tag", "name": "gloves", "url": "https://nhentai.net/tag/gloves/", "count": 5775}, {"id": 133055, "type": "tag", "name": "straitjacket", "url": "https://nhentai.net/tag/straitjacket/", "count": 4}]}