{"id": 390125, "media_id": "2128063", "title": {"english": "[frontierkiss (Kai Makoto)] Nanji no Teki o Aise Kouhen: Osuinu Dorei Shiiku Monogatari Dai 2-shou 2-wa (22b) [Digital]", "japanese": "", "chinese": null, "pretty": "Nanji no Teki o Aise Kouhen: Osuinu Dorei Shiiku Monogatari Dai 2wa"}, "languages": [{"id": 12227, "type": "language", "name": "english", "url": "https://nhentai.net/language/english/", "count": 92166}, {"id": 17249, "type": "language", "name": "translated", "url": "https://nhentai.net/language/translated/", "count": 155621}], "cover": {"media_id": "2128063", "width": 350, "height": 496, "mime": "jpg", "src": "https://t.nhentai.net/galleries/2128063/cover.jpg"}, "url": "https://nhentai.net/g/390125", "tags": [{"id": 12227, "type": "language", "name": "english", "url": "https://nhentai.net/language/english/", "count": 92166}, {"id": 13136, "type": "tag", "name": "facesitting", "url": "https://nhentai.net/tag/facesitting/", "count": 2191}, {"id": 14283, "type": "tag", "name": "anal", "url": "https://nhentai.net/tag/anal/", "count": 81460}, {"id": 15658, "type": "tag", "name": "bondage", "url": "https://nhentai.net/tag/bondage/", "count": 41367}, {"id": 16828, "type": "tag", "name": "hairy", "url": "https://nhentai.net/tag/hairy/", "count": 14645}, {"id": 17249, "type": "language", "name": "translated", "url": "https://nhentai.net/language/translated/", "count": 155621}, {"id": 21712, "type": "tag", "name": "males only", "url": "https://nhentai.net/tag/males-only/", "count": 31506}, {"id": 23044, "type": "artist", "name": "kai makoto", "url": "https://nhentai.net/artist/kai-makoto/", "count": 29}, {"id": 23895, "type": "tag", "name": "yaoi", "url": "https://nhentai.net/tag/yaoi/", "count": 38285}, {"id": 24676, "type": "tag", "name": "rimjob", "url": "https://nhentai.net/tag/rimjob/", "count": 5400}, {"id": 27473, "type": "tag", "name": "mosaic censorship", "url": "https://nhentai.net/tag/mosaic-censorship/", "count": 34685}, {"id": 29013, "type": "tag", "name": "dilf", "url": "https://nhentai.net/tag/dilf/", "count": 20001}, {"id": 29859, "type": "tag", "name": "blowjob", "url": "https://nhentai.net/tag/blowjob/", "count": 53088}, {"id": 30473, "type": "tag", "name": "muscle", "url": "https://nhentai.net/tag/muscle/", "count": 13859}, {"id": 31880, "type": "tag", "name": "bbm", "url": "https://nhentai.net/tag/bbm/", "count": 15646}, {"id": 33129, "type": "tag", "name": "slave", "url": "https://nhentai.net/tag/slave/", "count": 3572}, {"id": 33172, "type": "category", "name": "doujinshi", "url": "https://nhentai.net/category/doujinshi/", "count": 292796}, {"id": 73750, "type": "tag", "name": "bald", "url": "https://nhentai.net/tag/bald/", "count": 4379}, {"id": 90671, "type": "parody", "name": "original", "url": "https://nhentai.net/parody/original/", "count": 46664}, {"id": 104245, "type": "tag", "name": "small penis", "url": "https://nhentai.net/tag/small-penis/", "count": 864}, {"id": 107705, "type": "tag", "name": "facial hair", "url": "https://nhentai.net/tag/facial-hair/", "count": 2086}, {"id": 130025, "type": "tag", "name": "anal intercourse", "url": "https://nhentai.net/tag/anal-intercourse/", "count": 3732}]}