{"id": "399361", "media_id": "2193785", "title": {"english": "[saluky] Shamare's Pre Employment Screening [Arknights]", "japanese": "[saluky] \u5deb\u604b\u7684\u5165\u804c\u4f53\u68c0 (\u660e\u65e5\u65b9\u821f) [\u4e2d\u56fd\u8a9e]", "chinese": null, "pretty": "Shamare's Pre Employment Screening"}, "languages": [{"id": 12227, "type": "language", "name": "english", "url": "https://nhentai.net/language/english/", "count": 92725}, {"id": 17249, "type": "language", "name": "translated", "url": "https://nhentai.net/language/translated/", "count": 156814}], "cover": {"media_id": "2193785", "width": 350, "height": 495, "mime": "jpg", "src": "https://t.nhentai.net/galleries/2193785/cover.jpg"}, "url": "https://nhentai.net/g/399361", "tags": [{"id": 683, "type": "tag", "name": "squirting", "url": "https://nhentai.net/tag/squirting/", "count": 2814}, {"id": 6817, "type": "tag", "name": "unusual pupils", "url": "https://nhentai.net/tag/unusual-pupils/", "count": 10450}, {"id": 7155, "type": "tag", "name": "cunnilingus", "url": "https://nhentai.net/tag/cunnilingus/", "count": 6793}, {"id": 9661, "type": "tag", "name": "cervix penetration", "url": "https://nhentai.net/tag/cervix-penetration/", "count": 3680}, {"id": 12227, "type": "language", "name": "english", "url": "https://nhentai.net/language/english/", "count": 92725}, {"id": 13720, "type": "tag", "name": "nakadashi", "url": "https://nhentai.net/tag/nakadashi/", "count": 59141}, {"id": 13989, "type": "tag", "name": "ahegao", "url": "https://nhentai.net/tag/ahegao/", "count": 37411}, {"id": 17249, "type": "language", "name": "translated", "url": "https://nhentai.net/language/translated/", "count": 156814}, {"id": 19440, "type": "tag", "name": "lolicon", "url": "https://nhentai.net/tag/lolicon/", "count": 82261}, {"id": 20035, "type": "tag", "name": "x-ray", "url": "https://nhentai.net/tag/x-ray/", "count": 27216}, {"id": 20525, "type": "tag", "name": "defloration", "url": "https://nhentai.net/tag/defloration/", "count": 28100}, {"id": 21283, "type": "tag", "name": "masked face", "url": "https://nhentai.net/tag/masked-face/", "count": 2522}, {"id": 24380, "type": "tag", "name": "pantyhose", "url": "https://nhentai.net/tag/pantyhose/", "count": 18259}, {"id": 27553, "type": "tag", "name": "rape", "url": "https://nhentai.net/tag/rape/", "count": 42988}, {"id": 29859, "type": "tag", "name": "blowjob", "url": "https://nhentai.net/tag/blowjob/", "count": 53539}, {"id": 30555, "type": "tag", "name": "big penis", "url": "https://nhentai.net/tag/big-penis/", "count": 14525}, {"id": 31285, "type": "tag", "name": "fox girl", "url": "https://nhentai.net/tag/fox-girl/", "count": 3187}, {"id": 33172, "type": "category", "name": "doujinshi", "url": "https://nhentai.net/category/doujinshi/", "count": 294585}, {"id": 35762, "type": "tag", "name": "sole female", "url": "https://nhentai.net/tag/sole-female/", "count": 99767}, {"id": 35763, "type": "tag", "name": "sole male", "url": "https://nhentai.net/tag/sole-male/", "count": 89141}, {"id": 81774, "type": "tag", "name": "kemonomimi", "url": "https://nhentai.net/tag/kemonomimi/", "count": 11505}, {"id": 85295, "type": "tag", "name": "twintails", "url": "https://nhentai.net/tag/twintails/", "count": 16700}, {"id": 104227, "type": "tag", "name": "tail", "url": "https://nhentai.net/tag/tail/", "count": 4516}, {"id": 108082, "type": "parody", "name": "arknights", "url": "https://nhentai.net/parody/arknights/", "count": 297}, {"id": 121664, "type": "artist", "name": "saluky", "url": "https://nhentai.net/artist/saluky/", "count": 18}, {"id": 121710, "type": "character", "name": "doctor", "url": "https://nhentai.net/character/doctor/", "count": 70}, {"id": 123273, "type": "character", "name": "shamare", "url": "https://nhentai.net/character/shamare/", "count": 3}]}