{"id": 404677, "media_id": "2231531", "title": {"english": "[KeinV] \u732e\u7cbe", "japanese": "[KeinV] \u732e\u7cbe", "chinese": null, "pretty": "\u732e\u7cbe"}, "languages": [{"id": 6346, "type": "language", "name": "japanese", "url": "https://nhentai.net/language/japanese/", "count": 228661}], "cover": {"media_id": "2231531", "width": 350, "height": 494, "mime": "jpg", "src": "https://t.nhentai.net/galleries/2231531/cover.jpg"}, "url": "https://nhentai.net/g/404677", "tags": [{"id": 2937, "type": "tag", "name": "big breasts", "url": "https://nhentai.net/tag/big-breasts/", "count": 133503}, {"id": 6346, "type": "language", "name": "japanese", "url": "https://nhentai.net/language/japanese/", "count": 228661}, {"id": 6525, "type": "tag", "name": "nurse", "url": "https://nhentai.net/tag/nurse/", "count": 4016}, {"id": 33172, "type": "category", "name": "doujinshi", "url": "https://nhentai.net/category/doujinshi/", "count": 295801}, {"id": 90671, "type": "parody", "name": "original", "url": "https://nhentai.net/parody/original/", "count": 48391}, {"id": 135844, "type": "artist", "name": "maskwolf", "url": "https://nhentai.net/artist/maskwolf/", "count": 19}]}