{"id": 406842, "media_id": "2245769", "title": {"english": "[Amary] I'll take away Hajimete... !! ~ I've become my good-looking childhood friend ~ 2 (Amariris Comics)", "japanese": "[Amary] \u30ef\u30bf\u30b7\u306e\u30cf\u30b8\u30e1\u30c6\u596a\u3044\u307e\u3059\u2026!!~\u30a4\u30b1\u30e1\u30f3\u5e7c\u99b4\u67d3\u306b\u306a\u3063\u305f\u79c1~ 2\u8a71 (\u30a2\u30de\u30ea\u30ea\u30b9\u30b3\u30df\u30c3\u30af\u30b9)", "chinese": null, "pretty": "I'll take away Hajimete... !!2"}, "languages": [{"id": 6346, "type": "language", "name": "japanese", "url": "https://nhentai.net/language/japanese/", "count": 228683}], "cover": {"media_id": "2245769", "width": 350, "height": 494, "mime": "jpg", "src": "https://t.nhentai.net/galleries/2245769/cover.jpg"}, "url": "https://nhentai.net/g/406842", "tags": [{"id": 6346, "type": "language", "name": "japanese", "url": "https://nhentai.net/language/japanese/", "count": 228683}, {"id": 8378, "type": "tag", "name": "glasses", "url": "https://nhentai.net/tag/glasses/", "count": 58224}, {"id": 9162, "type": "tag", "name": "masturbation", "url": "https://nhentai.net/tag/masturbation/", "count": 12894}, {"id": 11089, "type": "tag", "name": "body swap", "url": "https://nhentai.net/tag/body-swap/", "count": 1387}, {"id": 33173, "type": "category", "name": "manga", "url": "https://nhentai.net/category/manga/", "count": 98547}, {"id": 138200, "type": "tag", "name": "gender change", "url": "https://nhentai.net/tag/gender-change/", "count": 63}]}